lazymp
