Metadata-Version: 1.0
Name: lazymp
Version: 0.1.0.0.3
Summary: This is an Example Package
Home-page: http://leohung.net/pymp
Author: San-Chuan Hung
Author-email: sanchuah@andrew.cmu.edu
License: MIT
Keywords: easy lazy openmp parallel
Platform: UNKNOWN
